README.md
setup.py
bin/pantilt
piservopantilt/__init__.py
piservopantilt/servo_control.py
piservopantilt/servo_details.py
piservopantilt.egg-info/PKG-INFO
piservopantilt.egg-info/SOURCES.txt
piservopantilt.egg-info/dependency_links.txt
piservopantilt.egg-info/requires.txt
piservopantilt.egg-info/top_level.txt