Metadata-Version: 2.1
Name: piservopantilt
Version: 0.2.1
Summary: Scripts to control servos in pan-tilt configuration with Raspberry Pi
Home-page: https://github.com/kangasta/piservopantilt
Author: Toni Kangas
License: UNKNOWN
Platform: UNKNOWN
Classifier: Programming Language :: Python :: 2.7
Classifier: Programming Language :: Python :: 3
Classifier: License :: OSI Approved :: MIT License
Classifier: Operating System :: OS Independent
